{
  "th": {
    "nav_home": "หน้าแรก",
    "nav_about": "เกี่ยวกับเรา",
    "nav_services": "บริการ",
    "nav_portfolio": "ผลงาน",
    "nav_blog": "บทความ",
    "nav_contact": "ติดต่อเรา",
    "cta_quote": "ขอใบเสนอราคา",
    "cta_contact": "ติดต่อเรา",
    "cta_learn_more": "รู้จักเรา",
    "section_about_title": "เกี่ยวกับเรา",
    "about_desc": "บริษัท ยูฟิกซ์ เดคอร์ เซอร์วิส จำกัด เป็นผู้เชี่ยวชาญด้านงานวิศวกรรมอาคารและการบำรุงรักษาครบวงจร ด้วยประสบการณ์ที่ยาวนานและทีมงานมืออาชีพ เรามุ่งมั่นส่งมอบงานที่มีคุณภาพและมาตรฐานความปลอดภัยสูงสุด",
    "about_list_1": "งานโรยตัวอาคารสูง (Rope Access)",
    "about_list_2": "ระบบกันซึมและซ่อมรอยร้าว (Waterproofing)",
    "about_list_3": "งานทาสีและรีโนเวทอาคาร",
    "about_list_4": "งานระบบไฟฟ้าและประปา",
    "section_services_title": "บริการของเรา",
    "section_why_title": "ทำไมต้องเลือกเรา",
    "why_pro_title": "ทีมงานมืออาชีพ",
    "why_pro_desc": "ทีมงานวิศวกรและช่างผู้ชำนาญการ",
    "why_safety_title": "มาตรฐานความปลอดภัย",
    "why_safety_desc": "ปลอดภัย 100% ในทุกขั้นตอนการทำงาน",
    "why_time_title": "ตรงต่อเวลา",
    "why_time_desc": "ส่งมอบงานตามกำหนดการที่ชัดเจน",
    "section_portfolio_title": "ผลงานที่ผ่านมา",
    "section_blog_title": "บทความน่ารู้",
    "section_contact_title": "ติดต่อเรา",
    "contact_info_title": "ข้อมูลติดต่อ",
    "contact_form_title": "ส่งข้อความหาเรา",
    "form_name": "ชื่อ-นามสกุล",
    "form_email": "อีเมล",
    "form_phone": "เบอร์โทรศัพท์",
    "form_message": "ข้อความ",
    "form_submit": "ส่งข้อความ",
    "footer_desc": "ผู้นำด้านการซ่อมแซมและบำรุงรักษาอาคารอย่างมืออาชีพ ปลอดภัย และมีคุณภาพ",
    "footer_menu": "เมนู",
    "footer_legal": "กฎหมาย",
    "footer_privacy": "นโยบายความเป็นส่วนตัว",
    "footer_terms": "ข้อกำหนดและเงื่อนไข",
    "footer_cookie_policy": "นโยบายคุกกี้",
    "cookie_title": "ความพึงพอใจของคุณ",
    "cookie_desc": "เราใช้คุกกี้เพื่อเพิ่มประสิทธิภาพในการใช้งานเว็บไซต์...",
    "cookie_accept": "ยอมรับทั้งหมด",
    "cookie_reject": "ปฏิเสธ",
    "cookie_settings": "ตั้งค่าคุกกี้"
  },
  "en": {
    "nav_home": "Home",
    "nav_about": "About Us",
    "nav_services": "Services",
    "nav_portfolio": "Portfolio",
    "nav_blog": "Blog",
    "nav_contact": "Contact",
    "cta_quote": "Get a Quote",
    "cta_contact": "Contact Us",
    "cta_learn_more": "Learn More",
    "section_about_title": "About Us",
    "about_desc": "Ufix Decor Service Co., Ltd. is a specialist in integrated building engineering and maintenance. With extensive experience and a professional team, we are committed to delivering high-quality work and the highest safety standards.",
    "about_list_1": "Rope Access Services",
    "about_list_2": "Waterproofing and Crack Repair",
    "about_list_3": "Painting and Building Renovation",
    "about_list_4": "Electrical and Plumbing Systems",
    "section_services_title": "Our Services",
    "section_why_title": "Why Choose Us",
    "why_pro_title": "Professional Team",
    "why_pro_desc": "Expert engineers and skilled technicians",
    "why_safety_title": "Safety Standards",
    "why_safety_desc": "100% safe in every step of operation",
    "why_time_title": "On Time Delivery",
    "why_time_desc": "Delivery according to clear schedules",
    "section_portfolio_title": "Our Portfolio",
    "section_blog_title": "Blog & Articles",
    "section_contact_title": "Contact Us",
    "contact_info_title": "Contact Information",
    "contact_form_title": "Send Us a Message",
    "form_name": "Full Name",
    "form_email": "Email",
    "form_phone": "Phone Number",
    "form_message": "Message",
    "form_submit": "Send Message",
    "footer_desc": "Leading professional, safe, and quality building repair and maintenance specialist.",
    "footer_menu": "Menu",
    "footer_legal": "Legal",
    "footer_privacy": "Privacy Policy",
    "footer_terms": "Terms and Conditions",
    "footer_cookie_policy": "Cookie Policy",
    "cookie_title": "Your Privacy",
    "cookie_desc": "We use cookies to enhance your experience...",
    "cookie_accept": "Accept All",
    "cookie_reject": "Reject",
    "cookie_settings": "Cookie Settings"
  }
}
